{
  "$schema": "https://ui.shadcn.com/schema/registry-item.json",
  "name": "team-4",
  "type": "registry:block",
  "title": "Team Section 4",
  "description": "Shadcn/ui website team section for LayeredUI",
  "dependencies": [
    "framer-motion"
  ],
  "files": [
    {
      "path": "app/preview/team/four/page.tsx",
      "content": "'use client';\n\nimport { motion, type Variants } from 'framer-motion';\nimport { Badge } from '@/components/ui/badge';\n\nconst containerVariants: Variants = {\n  hidden: { opacity: 0 },\n  visible: {\n    opacity: 1,\n    transition: {\n      staggerChildren: 0.1,\n    },\n  },\n};\n\nconst headingVariants: Variants = {\n  hidden: { opacity: 0, y: 20 },\n  visible: {\n    opacity: 1,\n    y: 0,\n    transition: {\n      duration: 0.8,\n      delay: 0.2,\n      ease: 'easeOut',\n    },\n  },\n};\n\nconst descriptionVariants: Variants = {\n  hidden: { opacity: 0, y: 15 },\n  visible: {\n    opacity: 1,\n    y: 0,\n    transition: {\n      duration: 0.8,\n      delay: 0.3,\n      ease: 'easeOut',\n    },\n  },\n};\n\nconst badgeVariants: Variants = {\n  hidden: { opacity: 0, scale: 0.8 },\n  visible: {\n    opacity: 1,\n    scale: 1,\n    transition: {\n      duration: 0.6,\n      ease: 'easeOut',\n    },\n  },\n};\n\nconst lineVariants: Variants = {\n  hidden: { scaleX: 0 },\n  visible: {\n    scaleX: 1,\n    transition: {\n      duration: 0.8,\n      ease: 'easeInOut',\n    },\n  },\n};\n\nconst customersVariants: Variants = {\n  hidden: { opacity: 0, y: 20 },\n  visible: {\n    opacity: 1,\n    y: 0,\n    transition: {\n      duration: 0.8,\n      delay: 0.7,\n      ease: 'easeOut',\n    },\n  },\n};\n\nconst contributors = [\n  { id: 1, name: 'John Doe', avatar: 'https://api.dicebear.com/7.x/avataaars/svg?seed=JohnDoe', github: 'https://github.com' },\n  { id: 2, name: 'Jane Smith', avatar: 'https://api.dicebear.com/7.x/avataaars/svg?seed=JaneSmith', github: 'https://github.com' },\n  { id: 3, name: 'Mike Johnson', avatar: 'https://api.dicebear.com/7.x/avataaars/svg?seed=MikeJohnson', github: 'https://github.com' },\n  { id: 4, name: 'Sarah Williams', avatar: 'https://api.dicebear.com/7.x/avataaars/svg?seed=SarahWilliams', github: 'https://github.com' },\n  { id: 5, name: 'Tom Brown', avatar: 'https://api.dicebear.com/7.x/avataaars/svg?seed=TomBrown', github: 'https://github.com' },\n  { id: 6, name: 'Emma Davis', avatar: 'https://api.dicebear.com/7.x/avataaars/svg?seed=EmmaDavis', github: 'https://github.com' },\n  { id: 7, name: 'David Miller', avatar: 'https://api.dicebear.com/7.x/avataaars/svg?seed=DavidMiller', github: 'https://github.com' },\n  { id: 8, name: 'Lisa Anderson', avatar: 'https://api.dicebear.com/7.x/avataaars/svg?seed=LisaAnderson', github: 'https://github.com' },\n  { id: 9, name: 'James Taylor', avatar: 'https://api.dicebear.com/7.x/avataaars/svg?seed=JamesTaylor', github: 'https://github.com' },\n  { id: 10, name: 'Rachel White', avatar: 'https://api.dicebear.com/7.x/avataaars/svg?seed=RachelWhite', github: 'https://github.com' },\n];\n\nexport default function ContributorsSection() {\n  return (\n    <section className=\"relative py-16 md:py-32\">\n      <div className=\"max-w-5xl mx-auto px-4 sm:px-6 lg:px-8\">\n        <motion.div\n          className=\"flex flex-col items-center text-center\"\n          initial=\"hidden\"\n          whileInView=\"visible\"\n          viewport={{ once: true, amount: 0.3 }}\n          variants={containerVariants}\n        >\n          {/* Badge */}\n          <motion.div\n            className=\"flex items-center gap-3 sm:gap-4 mb-6 sm:mb-8\"\n            variants={containerVariants}\n          >\n            <motion.div className=\"flex items-center\" variants={lineVariants}>\n              <div className=\"w-12 sm:w-20 h-px bg-gradient-to-r from-transparent via-primary/30 to-transparent\" />\n            </motion.div>\n\n            <motion.div variants={badgeVariants}>\n              <Badge variant=\"hero\" className=\"group\">\n                <span className=\"text-sm font-normal\">Community</span>\n              </Badge>\n            </motion.div>\n\n            <motion.div className=\"flex items-center\" variants={lineVariants}>\n              <div className=\"w-12 sm:w-20 h-px bg-gradient-to-l from-transparent via-primary/30 to-transparent\" />\n            </motion.div>\n          </motion.div>\n\n          {/* Heading */}\n          <motion.h2\n            className=\"text-3xl sm:text-4xl md:text-5xl font-normal leading-tight text-foreground max-w-3xl\"\n            variants={headingVariants}\n          >\n            Built by the Community <br /> for the Community\n          </motion.h2>\n\n          {/* Description */}\n          <motion.p\n            className=\"mt-6 text-muted-foreground text-sm sm:text-base font-normal leading-relaxed\"\n            variants={descriptionVariants}\n          >\n            Join our community of passionate developers and designers\n          </motion.p>\n\n          {/* Contributors Grid */}\n          <motion.div\n            className=\"mx-auto mt-12 flex max-w-lg flex-wrap justify-center gap-3\"\n            variants={customersVariants}\n          >\n            {contributors.map((contributor, index) => (\n              <motion.a\n                key={contributor.id}\n                href={contributor.github}\n                target=\"_blank\"\n                rel=\"noopener noreferrer\"\n                title={contributor.name}\n                className=\"size-16 rounded-full border border-border hover:border-primary/50 transition-all duration-300 hover:shadow-lg group overflow-hidden flex items-center justify-center bg-muted\"\n                initial={{ opacity: 0, scale: 0.8 }}\n                whileInView={{ opacity: 1, scale: 1 }}\n                transition={{\n                  delay: index * 0.05,\n                  duration: 0.6,\n                  ease: 'easeOut',\n                }}\n                viewport={{ once: true }}\n                whileHover={{ scale: 1.15 }}\n              >\n                <img\n                  alt={contributor.name}\n                  src={contributor.avatar}\n                  loading=\"lazy\"\n                  width={64}\n                  height={64}\n                  className=\"w-full h-full rounded-full object-cover\"\n                />\n              </motion.a>\n            ))}\n          </motion.div>\n        </motion.div>\n      </div>\n    </section>\n  );\n}\n",
      "type": "registry:component",
      "target": "components/team.tsx"
    },

    {
      "path": "components/ui/badge.tsx",
      "type": "registry:component",
      "target": "components/ui/badge.tsx",
      "content": "import type * as React from \"react\"\nimport { Slot } from \"@radix-ui/react-slot\"\nimport { cva, type VariantProps } from \"class-variance-authority\"\n\nimport { cn } from \"@/lib/utils\"\n\nconst badgeVariants = cva(\n  \"inline-flex items-center justify-center rounded-md border px-2 py-0.5 text-xs font-medium w-fit whitespace-nowrap shrink-0 [&>svg]:size-3 gap-1 [&>svg]:pointer-events-none focus-visible:border-ring focus-visible:ring-ring/50 focus-visible:ring-[3px] aria-invalid:ring-destructive/20 dark:aria-invalid:ring-destructive/40 aria-invalid:border-destructive transition-[color,box-shadow] overflow-hidden\",\n  {\n    variants: {\n      variant: {\n        default: \"border-transparent bg-primary text-primary-foreground [a&]:hover:bg-primary/90\",\n        secondary: \"border-transparent bg-secondary text-secondary-foreground [a&]:hover:bg-secondary/90\",\n        destructive:\n          \"border-transparent bg-destructive text-white [a&]:hover:bg-destructive/90 focus-visible:ring-destructive/20 dark:focus-visible:ring-destructive/40 dark:bg-destructive/60\",\n        outline: \"text-foreground [a&]:hover:bg-accent [a&]:hover:text-accent-foreground\",\n        hero: \"border-border/50 bg-secondary/50 text-foreground backdrop-blur-sm px-4 py-2 rounded-full\",\n      },\n    },\n    defaultVariants: {\n      variant: \"default\",\n    },\n  },\n)\n\nfunction Badge({\n  className,\n  variant,\n  asChild = false,\n  ...props\n}: React.ComponentProps<\"span\"> & VariantProps<typeof badgeVariants> & { asChild?: boolean }) {\n  const Comp = asChild ? Slot : \"span\"\n\n  return <Comp data-slot=\"badge\" className={cn(badgeVariants({ variant }), className)} {...props} />\n}\n\nexport { Badge, badgeVariants }"
    }
  ]
}